serdes/__init__.py
serdes/arrow.py
serdes/avro.py
serdes-0.0.2.dist-info/METADATA
serdes-0.0.2.dist-info/WHEEL
serdes-0.0.2.dist-info/dependency_links.txt
serdes-0.0.2.dist-info/top_level.txt
serdes-0.0.2.dist-info/RECORD
