Metadata-Version: 2.1
Name: serdes
Version: 0.0.2
Author: Woojin Cho
Author-email: woojin.cho@gmail.com
License: MIT License
Requires-Python: >=3.8
Requires-Dist: dataclasses-avroschema
Requires-Dist: fastavro
Requires-Dist: pyarrow
